noteshrink.py
noteshrink-0.1.0.dist-info/DESCRIPTION.rst
noteshrink-0.1.0.dist-info/METADATA
noteshrink-0.1.0.dist-info/RECORD
noteshrink-0.1.0.dist-info/WHEEL
noteshrink-0.1.0.dist-info/entry_points.txt
noteshrink-0.1.0.dist-info/metadata.json
noteshrink-0.1.0.dist-info/top_level.txt
